[{"id": 231802979, "amount": 9, "quality": 0, "kind": {"name": "Power", "image": "images/resources/power.png", "db_letter": 1, "transportation": 0, "retailable": false, "research": false, "exchangeTradable": true}, "blocked": false, "cost": {"workers": 0.0, "admin": 0.0, "material1": 0.0, "material2": 0.0, "material3": 0.0, "material4": 0.0, "material5": 0.0, "market": 2.1066655930243905}, "materials": ["", "", "", "", ""]}, {"id": 231657335, "amount": 3, "quality": 2, "kind": {"name": "Power", "image": "images/resources/power.png", "db_letter": 1, "transportation": 0, "retailable": false, "research": false, "exchangeTradable": true}, "blocked": false, "cost": {"workers": 0.0, "admin": 0.0, "material1": 0.0, "material2": 0.0, "material3": 0.0, "material4": 0.0, "material5": 0.0, "market": 0.7171456914232854}, "materials": ["", "", "", "", ""]}, {"id": 219913795, "amount": 370, "quality": 0, "kind": {"name": "Water", "image": "images/resources/water.png", "db_letter": 2, "transportation": 0, "retailable": false, "research": false, "exchangeTradable": true}, "blocked": false, "cost": {"workers": 0.0, "admin": 0.0, "material1": 0.0, "material2": 0.0, "material3": 0.0, "material4": 0.0, "material5": 0.0, "market": 109.56183745583033}, "materials": ["Power", "", "", "", ""]}, {"id": 219646191, "amount": 40, "quality": 1, "kind": {"name": "Water", "image": "images/resources/water.png", "db_letter": 2, "transportation": 0, "retailable": false, "research": false, "exchangeTradable": true}, "blocked": false, "cost": {"workers": 0.0, "admin": 0.0, "material1": 0.0, "material2": 0.0, "material3": 0.0, "material4": 0.0, "material5": 0.0, "market": 11.520547945205525}, "materials": ["Power", "", "", "", ""]}, {"id": 231930166, "amount": 620, "quality": 0, "kind": {"name": "Diesel", "image": "images/resources/diesel.png", "db_letter": 12, "transportation": 1, "retailable": true, "research": false, "exchangeTradable": true}, "blocked": false, "cost": {"workers": 0.0, "admin": 0.0, "material1": 0.0, "material2": 0.0, "material3": 0.0, "material4": 0.0, "material5": 0.0, "market": 22630.0}, "materials": ["Power", "Crude oil", "Ethanol", "", ""]}, {"id": 231589209, "amount": 34, "quality": 2, "kind": {"name": "Diesel", "image": "images/resources/diesel.png", "db_letter": 12, "transportation": 1, "retailable": true, "research": false, "exchangeTradable": true}, "blocked": false, "cost": {"workers": 0.0, "admin": 0.0, "material1": 0.0, "material2": 0.0, "material3": 0.0, "material4": 0.0, "material5": 0.0, "market": 1258.0}, "materials": ["Power", "Crude oil", "Ethanol", "", ""]}, {"id": 224037009, "amount": 20100, "quality": 0, "kind": {"name": "Transport", "image": "images/resources/transport.png", "db_letter": 13, "transportation": 0, "retailable": null, "research": false, "exchangeTradable": true}, "blocked": false, "cost": {"workers": 0.0, "admin": 0.0, "material1": 0.0, "material2": 0.0, "material3": 0.0, "material4": 0.0, "material5": 0.0, "market": 7153.656006440584}, "materials": ["Power", "Diesel", "", "", ""]}, {"id": 231657410, "amount": 1, "quality": 1, "kind": {"name": "Bauxite", "image": "images/resources/bauxite.png", "db_letter": 15, "transportation": 1, "retailable": false, "research": false, "exchangeTradable": true}, "blocked": false, "cost": {"workers": 0.0, "admin": 0.0, "material1": 0.0, "material2": 0.0, "material3": 0.0, "material4": 0.0, "material5": 0.0, "market": 7.599999999999399}, "materials": ["Power", "Water", "", "", ""]}, {"id": 231808196, "amount": 2631, "quality": 0, "kind": {"name": "Silicon", "image": "images/resources/silicon.png", "db_letter": 16, "transportation": 1, "retailable": false, "research": false, "exchangeTradable": true}, "blocked": false, "cost": {"workers": 7001.46008022538, "admin": 988.620765545765, "material1": 1870.9064025794564, "material2": 5555.7513681592045, "material3": 0.0, "material4": 0.0, "material5": 0.0, "market": 0.0}, "materials": ["Power", "Sand", "", "", ""]}, {"id": 231657529, "amount": 1, "quality": 1, "kind": {"name": "Silicon", "image": "images/resources/silicon.png", "db_letter": 16, "transportation": 1, "retailable": false, "research": false, "exchangeTradable": true}, "blocked": false, "cost": {"workers": 0.0, "admin": 0.0, "material1": 0.0, "material2": 0.0, "material3": 0.0, "material4": 0.0, "material5": 0.0, "market": 7.400570206700037}, "materials": ["Power", "Sand", "", "", ""]}, {"id": 231860893, "amount": 4, "quality": 2, "kind": {"name": "Chemicals", "image": "images/resources/chemicals.png", "db_letter": 17, "transportation": 1, "retailable": false, "research": false, "exchangeTradable": true}, "blocked": false, "cost": {"workers": 0.0, "admin": 0.0, "material1": 0.0, "material2": 0.0, "material3": 0.0, "material4": 0.0, "material5": 0.0, "market": 56.000000000001016}, "materials": ["Power", "Minerals", "", "", ""]}, {"id": 231682676, "amount": 4099, "quality": 0, "kind": {"name": "Aluminium", "image": "images/resources/aluminium.png", "db_letter": 18, "transportation": 1, "retailable": false, "research": false, "exchangeTradable": true}, "blocked": false, "cost": {"workers": 14024.589445598875, "admin": 1914.184275453529, "material1": 14579.101445525632, "material2": 29627.802478517933, "material3": 0.0, "material4": 0.0, "material5": 0.0, "market": 0.0}, "materials": ["Power", "Bauxite", "", "", ""]}, {"id": 231876133, "amount": 168, "quality": 1, "kind": {"name": "Processors", "image": "images/resources/processors.png", "db_letter": 20, "transportation": 1, "retailable": false, "research": false, "exchangeTradable": true}, "blocked": false, "cost": {"workers": 6863.73535482099, "admin": 1049.9979785123433, "material1": 3937.6846637379667, "material2": 2335.2928176795585, "material3": 0.0, "material4": 0.0, "material5": 0.0, "market": 0.0}, "materials": ["Silicon", "Chemicals", "", "", ""]}, {"id": 231301450, "amount": 1531, "quality": 0, "kind": {"name": "Electronic components", "image": "images/resources/electronic-components.png", "db_letter": 21, "transportation": 1, "retailable": false, "research": false, "exchangeTradable": true}, "blocked": false, "cost": {"workers": 13899.971995014468, "admin": 1616.4115864907433, "material1": 27091.01822670145, "material2": 20302.181761004882, "material3": 0.0, "material4": 0.0, "material5": 0.0, "market": 0.0}, "materials": ["Silicon", "Chemicals", "", "", ""]}, {"id": 231468215, "amount": 2601, "quality": 0, "kind": {"name": "Batteries", "image": "images/resources/batteries.png", "db_letter": 22, "transportation": 1, "retailable": false, "research": false, "exchangeTradable": true}, "blocked": false, "cost": {"workers": 38641.93865344025, "admin": 4911.983962382657, "material1": 139270.19106653836, "material2": 0.0, "material3": 0.0, "material4": 0.0, "material5": 0.0, "market": 0.0}, "materials": ["Chemicals", "", "", "", ""]}, {"id": 230755090, "amount": 3, "quality": 0, "kind": {"name": "Steel", "image": "images/resources/steel.png", "db_letter": 43, "transportation": 1, "retailable": false, "research": false, "exchangeTradable": true}, "blocked": false, "cost": {"workers": 2.2990194760682567, "admin": 0.25730033245700307, "material1": 1.2591212254503306, "material2": 1.36170374319544, "material3": 4.325197722617697, "material4": 0.0, "material5": 0.0, "market": 23.090537383178212}, "materials": ["Power", "Chemicals", "Iron ore", "", ""]}, {"id": 231460476, "amount": 2, "quality": 1, "kind": {"name": "Sand", "image": "images/resources/sand.png", "db_letter": 44, "transportation": 1, "retailable": false, "research": false, "exchangeTradable": true}, "blocked": false, "cost": {"workers": 0.0, "admin": 0.0, "material1": 0.0, "material2": 0.0, "material3": 0.0, "material4": 0.0, "material5": 0.0, "market": 2.240072859745039}, "materials": ["Power", "", "", "", ""]}, {"id": 231597250, "amount": 2099, "quality": 0, "kind": {"name": "Glass", "image": "images/resources/glass.png", "db_letter": 45, "transportation": 1, "retailable": false, "research": false, "exchangeTradable": true}, "blocked": false, "cost": {"workers": 6702.880140658185, "admin": 867.9512026606264, "material1": 1003.5278598699009, "material2": 14018.201900245347, "material3": 0.0, "material4": 0.0, "material5": 0.0, "market": 0.0}, "materials": ["Power", "Silicon", "", "", ""]}, {"id": 231803008, "amount": 1416, "quality": 0, "kind": {"name": "Steel beams", "image": "images/resources/steel-beams.png", "db_letter": 107, "transportation": 5, "retailable": false, "research": false, "exchangeTradable": true}, "blocked": false, "cost": {"workers": 5198.3793014125, "admin": 781.4323924281149, "material1": 1328.5991296339541, "material2": 14858.164359827333, "material3": 0.0, "material4": 0.0, "material5": 0.0, "market": 0.0}, "materials": ["Power", "Steel", "", "", ""]}, {"id": 216965712, "amount": 1451, "quality": 0, "kind": {"name": "Planks", "image": "images/resources/planks.png", "db_letter": 108, "transportation": 1, "retailable": true, "research": false, "exchangeTradable": true}, "blocked": false, "cost": {"workers": 289.4886803073905, "admin": 27.285160148351597, "material1": 130.09489680309582, "material2": 0.0, "material3": 0.0, "material4": 0.0, "material5": 0.0, "market": 12576.978655314966}, "materials": ["Wood", "", "", "", ""]}, {"id": 231682666, "amount": 195, "quality": 0, "kind": {"name": "Windows", "image": "images/resources/windows.png", "db_letter": 109, "transportation": 1, "retailable": true, "research": false, "exchangeTradable": true}, "blocked": false, "cost": {"workers": 5567.943931597664, "admin": 795.6879226113244, "material1": 5858.616590142512, "material2": 2060.333998840755, "material3": 0.0, "material4": 0.0, "material5": 0.0, "market": 0.0}, "materials": ["Aluminium", "Glass", "", "", ""]}, {"id": 231663399, "amount": 264, "quality": 0, "kind": {"name": "Tools", "image": "images/resources/tools.png", "db_letter": 110, "transportation": 1, "retailable": true, "research": false, "exchangeTradable": true}, "blocked": false, "cost": {"workers": 4845.9468064014845, "admin": 708.3853664434579, "material1": 10845.378353165417, "material2": 18391.510167500965, "material3": 1221.4888324642754, "material4": 1184.8021060094707, "material5": 0.0, "market": 0.0}, "materials": ["Electronic components", "Batteries", "Steel", "Planks", ""]}, {"id": 231936921, "amount": 11, "quality": 0, "kind": {"name": "Construction units", "image": "images/resources/construction-units.png", "db_letter": 111, "transportation": 0, "retailable": false, "research": false, "exchangeTradable": true}, "blocked": false, "cost": {"workers": 3811.499999999999, "admin": 599.3333333333338, "material1": 2027.5, "material2": 1334.7804364880155, "material3": 3221.9875391248925, "material4": 6191.2462509993375, "material5": 4125.0, "market": 0.0}, "materials": ["Diesel", "Steel beams", "Windows", "Tools", "Bulldozer"]}, {"id": 231948166, "amount": 10, "quality": 0, "kind": {"name": "Bulldozer", "image": "images/resources/bulldozer.png", "db_letter": 112, "transportation": 5, "retailable": false, "research": false, "exchangeTradable": true}, "blocked": false, "cost": {"workers": 0.0, "admin": 0.0, "material1": 0.0, "material2": 0.0, "material3": 0.0, "material4": 0.0, "material5": 0.0, "market": 30000.0}, "materials": ["Steel", "Car body", "Combustion engine", "", ""]}]